colanderalchemy/__init__.py
colanderalchemy/schema.py
ColanderAlchemy-0.3.4.dist-info/AUTHORS.txt
ColanderAlchemy-0.3.4.dist-info/LICENSE.txt
ColanderAlchemy-0.3.4.dist-info/METADATA
ColanderAlchemy-0.3.4.dist-info/WHEEL
ColanderAlchemy-0.3.4.dist-info/top_level.txt
ColanderAlchemy-0.3.4.dist-info/zip-safe
ColanderAlchemy-0.3.4.dist-info/RECORD
