Metadata-Version: 2.1
Name: ColanderAlchemy
Version: 0.3.4
Summary: Autogenerate Colander schemas based on SQLAlchemy models.
Home-page: https://github.com/stefanofontanelli/ColanderAlchemy
Author: Stefano Fontanelli
Author-email: s.fontanelli@asidev.com
License: MIT
Keywords: serialize deserialize validate schema validation colander sqlalchemy
Platform: UNKNOWN
Classifier: Development Status :: 4 - Beta
Classifier: Intended Audience :: Developers
Classifier: Programming Language :: Python
Classifier: Programming Language :: Python :: 2
Classifier: Programming Language :: Python :: 2.6
Classifier: Programming Language :: Python :: 2.7
Classifier: Programming Language :: Python :: 3
Classifier: Programming Language :: Python :: 3.2
Classifier: Programming Language :: Python :: 3.3
Classifier: Programming Language :: Python :: 3.4
Classifier: Programming Language :: Python :: 3.5
Classifier: Programming Language :: Python :: 3.6
Classifier: Programming Language :: Python :: 3.7
Classifier: Programming Language :: Python :: 3.8
Classifier: Programming Language :: Python :: Implementation :: CPython
Classifier: Programming Language :: Python :: Implementation :: PyPy
Classifier: License :: OSI Approved :: MIT License
Classifier: Operating System :: OS Independent
Classifier: Topic :: Database
Requires-Dist: colander (>=1.0b1)
Requires-Dist: SQLAlchemy (>=0.8dev)
